aimanual/__init__.py
aimanual/helper.py
aimanual-0.1.dist-info/LICENSE.txt
aimanual-0.1.dist-info/METADATA
aimanual-0.1.dist-info/WHEEL
aimanual-0.1.dist-info/top_level.txt
aimanual-0.1.dist-info/RECORD
