Metadata-Version: 2.1
Name: aimanual
Version: 0.1
Summary: A manual package for ai beginner
Home-page: https://github.com/
Author: Zoony
Author-email: onepage4you@gmail.com
License: UNKNOWN
Platform: UNKNOWN
Classifier: Programming Language :: Python :: 3
Classifier: License :: OSI Approved :: MIT License
Classifier: Operating System :: OS Independent
Requires-Python: >=3.6
License-File: LICENSE.txt
